precisetranscribe/__init__.py
precisetranscribe/__main__.py
precisetranscribe/gpt.py
precisetranscribe/openai.py
precisetranscribe/utils.py
precisetranscribe/whisper.py
precisetranscribe-0.2.1.dist-info/LICENSE
precisetranscribe-0.2.1.dist-info/METADATA
precisetranscribe-0.2.1.dist-info/WHEEL
precisetranscribe-0.2.1.dist-info/top_level.txt
precisetranscribe-0.2.1.dist-info/RECORD
