Metadata-Version: 2.1
Name: precisetranscribe
Version: 0.2.1
Summary: Utilities for transcribing audio files using the Whisper API.
Author-email: Aeron Laffere <ajlaffere@gmail.com>
Project-URL: Homepage, https://github.com/aeronjl/transcribe
Project-URL: Documentation, https://transcribe.readthedocs.io/
Project-URL: Repository, https://github.com/aeronjl/transcribe.git
Keywords: transcription
Classifier: License :: OSI Approved :: MIT License
Classifier: Programming Language :: Python
Classifier: Programming Language :: Python :: 3
Requires-Python: >=3.9
License-File: LICENSE
Requires-Dist: openai
Requires-Dist: numpy
Requires-Dist: ffmpeg-python
Requires-Dist: pydub
Requires-Dist: tiktoken
Requires-Dist: python-dotenv
Provides-Extra: dev
Requires-Dist: pytest ; extra == 'dev'
Requires-Dist: pytest-cov ; extra == 'dev'
